zeemee_py/__init__.py
zeemee_py/data_team_etl/all_partner_data_part1/ap1_module_data_processing/function_ap1_by_gender_create_one_school_data.py
zeemee_py/data_team_etl/all_partner_data_part1/ap1_module_data_processing/function_ap1_create_one_school_data.py
zeemee_py/data_team_etl/all_partner_data_part1/ap1_module_data_processing/function_common_ap1_calculate_values.py
zeemee_py/data_team_etl/all_partner_data_part1/ap1_module_data_processing/main_stitch_ap1_by_gender_for_config_schools.py
zeemee_py/data_team_etl/all_partner_data_part1/ap1_module_data_processing/main_stitch_ap1_by_gender_for_old_cohort.py
zeemee_py/data_team_etl/all_partner_data_part1/ap1_module_data_processing/main_stitch_ap1_for_config_schools.py
zeemee_py/data_team_etl/all_partner_data_part1/ap1_module_data_processing/main_stitch_ap1_for_old_cohort.py
zeemee_py/data_team_etl/all_partner_data_part1/ap1_module_data_processing/process_ap1_by_gender_for_config_schools.py
zeemee_py/data_team_etl/all_partner_data_part1/ap1_module_data_processing/process_ap1_by_gender_for_old_cohort.py
zeemee_py/data_team_etl/all_partner_data_part1/ap1_module_data_processing/process_ap1_for_config_schools.py
zeemee_py/data_team_etl/all_partner_data_part1/ap1_module_data_processing/process_ap1_for_old_cohort.py
zeemee_py/data_team_etl/all_partner_data_part1/ap1_module_table_update/function_ap1_perform_athena_update.py
zeemee_py/data_team_etl/all_partner_data_part1/ap1_module_table_update/function_ap1_recreate_full_table.py
zeemee_py/data_team_etl/all_partner_data_part2/ap2_module_data_processing/function_ap2_by_gender_create_one_school_data.py
zeemee_py/data_team_etl/all_partner_data_part2/ap2_module_data_processing/function_ap2_create_one_school_data.py
zeemee_py/data_team_etl/all_partner_data_part2/ap2_module_data_processing/function_common_ap2_calculate_values.py
zeemee_py/data_team_etl/all_partner_data_part2/ap2_module_data_processing/function_common_ap2_calculate_values_campus_visit.py
zeemee_py-0.0.1.2.dist-info/LICENSE
zeemee_py-0.0.1.2.dist-info/METADATA
zeemee_py-0.0.1.2.dist-info/WHEEL
zeemee_py-0.0.1.2.dist-info/top_level.txt
zeemee_py-0.0.1.2.dist-info/RECORD
