Metadata-Version: 2.1
Name: zeemee_py
Version: 0.0.1.2
Summary: Python packages for ZeeMee data-team
Author-email: Mayur Waghela <mayur@zeemee.com>
Project-URL: Homepage, https://github.com/zeemee/data-team
Project-URL: Issues, https://github.com/zeemee/data-team/issues
Classifier: Programming Language :: Python :: 3
Classifier: Operating System :: OS Independent
Requires-Python: >=3.11.8
License-File: LICENSE
Requires-Dist: pandas ==2.2.2
Requires-Dist: psycopg2 ==2.9.9
Requires-Dist: pyyaml ==6.0.1
Requires-Dist: redshift-connector ==2.1.1
Requires-Dist: pyathena ==3.8.2
Requires-Dist: build ==1.2.1
Requires-Dist: twine ==5.0.0
Requires-Dist: duckdb ==0.10.2
